botmerger/__init__.py
botmerger/base.py
botmerger/core.py
botmerger/errors.py
botmerger/experimental/__init__.py
botmerger/experimental/inquiry_bot.py
botmerger/ext/__init__.py
botmerger/ext/discord_integration.py
botmerger/models.py
botmerger/utils.py
botmerger-0.0.4.dist-info/LICENSE
botmerger-0.0.4.dist-info/METADATA
botmerger-0.0.4.dist-info/WHEEL
botmerger-0.0.4.dist-info/RECORD
