Metadata-Version: 2.1
Name: botmerger
Version: 0.0.4
Summary: 
License: MIT
Author: Oleksandr Tereshchenko
Author-email: toporok@gmail.com
Requires-Python: >=3.11,<4.0
Classifier: License :: OSI Approved :: MIT License
Classifier: Programming Language :: Python :: 3
Classifier: Programming Language :: Python :: 3.11
Provides-Extra: all
Provides-Extra: discord
Provides-Extra: langchain
Requires-Dist: pydantic (>=1,<2)
